fauxfactory/__init__.py
fauxfactory/constants.py
fauxfactory/facts.json
fauxfactory/helpers.py
fauxfactory/py.typed
fauxfactory/factories/__init__.py
fauxfactory/factories/booleans.py
fauxfactory/factories/choices.py
fauxfactory/factories/dates.py
fauxfactory/factories/internet.py
fauxfactory/factories/numbers.py
fauxfactory/factories/strings.py
fauxfactory/factories/structures.py
fauxfactory/factories/systems.py
fauxfactory-4.2.0.dist-info/METADATA
fauxfactory-4.2.0.dist-info/WHEEL
fauxfactory-4.2.0.dist-info/licenses/AUTHORS.rst
fauxfactory-4.2.0.dist-info/licenses/LICENSE
fauxfactory-4.2.0.dist-info/RECORD
