Metadata-Version: 2.4
Name: fauxfactory
Version: 4.2.0
Summary: Generates random data for your tests.
Project-URL: Changelog, https://github.com/omaciel/fauxfactory/blob/master/CHANGELOG.md
Project-URL: Homepage, https://github.com/omaciel/fauxfactory
Project-URL: Repository, https://github.com/omaciel/fauxfactory
Author-email: "Og B. Maciel" <omaciel@ogmaciel.com>
License: Apache-2.0
License-File: AUTHORS.rst
License-File: LICENSE
Keywords: automation,data,python,testing
Classifier: Development Status :: 5 - Production/Stable
Classifier: Intended Audience :: Developers
Classifier: License :: OSI Approved :: Apache Software License
Classifier: Natural Language :: English
Classifier: Operating System :: OS Independent
Classifier: Programming Language :: Python
Classifier: Programming Language :: Python :: 3.10
Classifier: Programming Language :: Python :: 3.11
Classifier: Programming Language :: Python :: 3.12
Classifier: Programming Language :: Python :: 3.13
Classifier: Programming Language :: Python :: 3.14
Classifier: Topic :: Software Development :: Testing
Requires-Python: >=3.10
Provides-Extra: dev
Requires-Dist: bandit>=1.7.0; extra == 'dev'
Requires-Dist: codecov>=2.1.13; extra == 'dev'
Requires-Dist: mypy>=1.8.0; extra == 'dev'
Requires-Dist: pytest-cov>=5.0.0; extra == 'dev'
Requires-Dist: pytest>=8.1.1; extra == 'dev'
Requires-Dist: ruff>=0.3.4; extra == 'dev'
Requires-Dist: twine>=5.0.0; extra == 'dev'
Requires-Dist: wheel>=0.43.0; extra == 'dev'
Provides-Extra: docs
Requires-Dist: sphinx; extra == 'docs'
Requires-Dist: sphinx-rtd-theme; extra == 'docs'
